shortkeygui/__init__.py
shortkeygui/main.py
shortkeygui-0.1.dist-info/LICENSE.txt
shortkeygui-0.1.dist-info/METADATA
shortkeygui-0.1.dist-info/WHEEL
shortkeygui-0.1.dist-info/top_level.txt
shortkeygui-0.1.dist-info/RECORD
