Metadata-Version: 2.1
Name: shortkeygui
Version: 0.1
Summary: ShortkeyGUI is an easy-to-use tool that can press a shortcut key. For Windows, macOS, and Linux, on Python 3 and 2.
Home-page: https://sribalaji.rf.gd
Author: Balaji Santhanam
Author-email: sribalaji2112@gmail.com
License: MIT
Keywords: ShortkeyPresser Created by SriBalaji shortcut key GUI
Classifier: Development Status :: 4 - Beta
Classifier: Environment :: Win32 (MS Windows)
Classifier: Environment :: X11 Applications
Classifier: Environment :: MacOS X
Classifier: Intended Audience :: Developers
Classifier: License :: OSI Approved :: MIT License
Classifier: Operating System :: OS Independent
Classifier: Programming Language :: Python :: 3.8
License-File: LICENSE.txt
Requires-Dist: uiaction
